{"nodes": [{"id": "c_users_hp_downloads_repochat_main_repochat_main_client_src_components_features_fileexplorer_jsx", "label": "FileExplorer.jsx", "file_type": "code", "source_file": "C:\\Users\\hp\\Downloads\\Repochat-main\\Repochat-main\\client\\src\\components\\features\\FileExplorer.jsx", "source_location": "L1"}, {"id": "fileexplorer_filenode", "label": "FileNode()", "file_type": "code", "source_file": "C:\\Users\\hp\\Downloads\\Repochat-main\\Repochat-main\\client\\src\\components\\features\\FileExplorer.jsx", "source_location": "L5"}, {"id": "fileexplorer_fileexplorer", "label": "FileExplorer()", "file_type": "code", "source_file": "C:\\Users\\hp\\Downloads\\Repochat-main\\Repochat-main\\client\\src\\components\\features\\FileExplorer.jsx", "source_location": "L50"}], "edges": [{"source": "c_users_hp_downloads_repochat_main_repochat_main_client_src_components_features_fileexplorer_jsx", "target": "react", "relation": "imports_from", "confidence": "EXTRACTED", "source_file": "C:\\Users\\hp\\Downloads\\Repochat-main\\Repochat-main\\client\\src\\components\\features\\FileExplorer.jsx", "source_location": "L1", "weight": 1.0}, {"source": "c_users_hp_downloads_repochat_main_repochat_main_client_src_components_features_fileexplorer_jsx", "target": "lucide_react", "relation": "imports_from", "confidence": "EXTRACTED", "source_file": "C:\\Users\\hp\\Downloads\\Repochat-main\\Repochat-main\\client\\src\\components\\features\\FileExplorer.jsx", "source_location": "L2", "weight": 1.0}, {"source": "c_users_hp_downloads_repochat_main_repochat_main_client_src_components_features_fileexplorer_jsx", "target": "c_users_hp_downloads_repochat_main_repochat_main_client_src_services_api", "relation": "imports_from", "confidence": "EXTRACTED", "source_file": "C:\\Users\\hp\\Downloads\\Repochat-main\\Repochat-main\\client\\src\\components\\features\\FileExplorer.jsx", "source_location": "L3", "weight": 1.0}, {"source": "c_users_hp_downloads_repochat_main_repochat_main_client_src_components_features_fileexplorer_jsx", "target": "fileexplorer_filenode", "relation": "contains", "confidence": "EXTRACTED", "source_file": "C:\\Users\\hp\\Downloads\\Repochat-main\\Repochat-main\\client\\src\\components\\features\\FileExplorer.jsx", "source_location": "L5", "weight": 1.0}, {"source": "c_users_hp_downloads_repochat_main_repochat_main_client_src_components_features_fileexplorer_jsx", "target": "fileexplorer_fileexplorer", "relation": "contains", "confidence": "EXTRACTED", "source_file": "C:\\Users\\hp\\Downloads\\Repochat-main\\Repochat-main\\client\\src\\components\\features\\FileExplorer.jsx", "source_location": "L50", "weight": 1.0}], "raw_calls": [{"caller_nid": "fileexplorer_filenode", "callee": "useState", "source_file": "C:\\Users\\hp\\Downloads\\Repochat-main\\Repochat-main\\client\\src\\components\\features\\FileExplorer.jsx", "source_location": "L6"}, {"caller_nid": "fileexplorer_filenode", "callee": "map", "source_file": "C:\\Users\\hp\\Downloads\\Repochat-main\\Repochat-main\\client\\src\\components\\features\\FileExplorer.jsx", "source_location": "L29"}, {"caller_nid": "fileexplorer_fileexplorer", "callee": "useState", "source_file": "C:\\Users\\hp\\Downloads\\Repochat-main\\Repochat-main\\client\\src\\components\\features\\FileExplorer.jsx", "source_location": "L51"}, {"caller_nid": "fileexplorer_fileexplorer", "callee": "useState", "source_file": "C:\\Users\\hp\\Downloads\\Repochat-main\\Repochat-main\\client\\src\\components\\features\\FileExplorer.jsx", "source_location": "L52"}, {"caller_nid": "fileexplorer_fileexplorer", "callee": "useState", "source_file": "C:\\Users\\hp\\Downloads\\Repochat-main\\Repochat-main\\client\\src\\components\\features\\FileExplorer.jsx", "source_location": "L53"}, {"caller_nid": "fileexplorer_fileexplorer", "callee": "useState", "source_file": "C:\\Users\\hp\\Downloads\\Repochat-main\\Repochat-main\\client\\src\\components\\features\\FileExplorer.jsx", "source_location": "L54"}, {"caller_nid": "fileexplorer_fileexplorer", "callee": "useState", "source_file": "C:\\Users\\hp\\Downloads\\Repochat-main\\Repochat-main\\client\\src\\components\\features\\FileExplorer.jsx", "source_location": "L55"}, {"caller_nid": "fileexplorer_fileexplorer", "callee": "useCallback", "source_file": "C:\\Users\\hp\\Downloads\\Repochat-main\\Repochat-main\\client\\src\\components\\features\\FileExplorer.jsx", "source_location": "L57"}, {"caller_nid": "fileexplorer_fileexplorer", "callee": "useEffect", "source_file": "C:\\Users\\hp\\Downloads\\Repochat-main\\Repochat-main\\client\\src\\components\\features\\FileExplorer.jsx", "source_location": "L83"}, {"caller_nid": "fileexplorer_fileexplorer", "callee": "map", "source_file": "C:\\Users\\hp\\Downloads\\Repochat-main\\Repochat-main\\client\\src\\components\\features\\FileExplorer.jsx", "source_location": "L160"}]}